README.rst
setup.py
sqlite_ucf/__init__.py
sqlite_ucf/tests.py
sqlite_ucf.egg-info/PKG-INFO
sqlite_ucf.egg-info/SOURCES.txt
sqlite_ucf.egg-info/dependency_links.txt
sqlite_ucf.egg-info/top_level.txt