Metadata-Version: 1.1
Name: sqlite-ucf
Version: 1.0.1
Summary: An alternate sqlite3.connect function that adds unicode case folding functionality.
Home-page: https://github.com/tim-mitchell/sqlite_ucf
Author: Tim Mitchell
Author-email: tim.mitchell@seequent.com
License: BSD
Keywords: sqlite unicode
Platform: UNKNOWN
Classifier: Programming Language :: Python :: 3.4
Classifier: Programming Language :: Python :: 3.5
Classifier: Programming Language :: Python :: 3.6
Classifier: License :: OSI Approved :: BSD License
